aiida_sssp_workflow/__init__.py
aiida_sssp_workflow/efermi.py
aiida_sssp_workflow/utils.py
aiida_sssp_workflow/version.py
aiida_sssp_workflow/calculations/__init__.py
aiida_sssp_workflow/calculations/birch_murnaghan_fit.py
aiida_sssp_workflow/calculations/calculate_bands_distance.py
aiida_sssp_workflow/calculations/calculate_metric.py
aiida_sssp_workflow/calculations/wien2k_ref.py
aiida_sssp_workflow/cli/__init__.py
aiida_sssp_workflow/cli/extract.py
aiida_sssp_workflow/cli/inspect.py
aiida_sssp_workflow/cli/run.py
aiida_sssp_workflow/cli/tools/__init__.py
aiida_sssp_workflow/cli/tools/dump.py
aiida_sssp_workflow/cli/tools/relabel.py
aiida_sssp_workflow/protocol/__init__.py
aiida_sssp_workflow/protocol/bands.yml
aiida_sssp_workflow/protocol/control.yml
aiida_sssp_workflow/protocol/converge.yml
aiida_sssp_workflow/protocol/criteria.yml
aiida_sssp_workflow/protocol/precision.yml
aiida_sssp_workflow/statics/__init__.py
aiida_sssp_workflow/statics/AE_EOS/AE-average-oxides.json
aiida_sssp_workflow/statics/AE_EOS/AE-average-unaries.json
aiida_sssp_workflow/statics/AE_EOS/WIEN2K_GS.json
aiida_sssp_workflow/statics/AE_EOS/WIEN2K_LANN.json
aiida_sssp_workflow/statics/AE_EOS/__init__.py
aiida_sssp_workflow/statics/structures/__init__.py
aiida_sssp_workflow/statics/structures/mapping.json
aiida_sssp_workflow/statics/structures/gs/Ag.cif
aiida_sssp_workflow/statics/structures/gs/Al.cif
aiida_sssp_workflow/statics/structures/gs/Ar.cif
aiida_sssp_workflow/statics/structures/gs/As.cif
aiida_sssp_workflow/statics/structures/gs/Au.cif
aiida_sssp_workflow/statics/structures/gs/B.cif
aiida_sssp_workflow/statics/structures/gs/Ba.cif
aiida_sssp_workflow/statics/structures/gs/Be.cif
aiida_sssp_workflow/statics/structures/gs/Bi.cif
aiida_sssp_workflow/statics/structures/gs/Br.cif
aiida_sssp_workflow/statics/structures/gs/C.cif
aiida_sssp_workflow/statics/structures/gs/Ca.cif
aiida_sssp_workflow/statics/structures/gs/Cd.cif
aiida_sssp_workflow/statics/structures/gs/CeN.cif
aiida_sssp_workflow-4.2.3.dist-info/LICENSE
aiida_sssp_workflow-4.2.3.dist-info/METADATA
aiida_sssp_workflow-4.2.3.dist-info/WHEEL
aiida_sssp_workflow-4.2.3.dist-info/entry_points.txt
aiida_sssp_workflow-4.2.3.dist-info/top_level.txt
aiida_sssp_workflow-4.2.3.dist-info/RECORD
