Metadata-Version: 2.1
Name: aiida_sssp_workflow
Version: 4.2.3
Summary: Package for the AiiDA SSSP workflow
Home-page: https://github.com/aiidateam/aiida-sssp-workflow
Author: Jusong Yu
Author-email: jusong.yu@psi.ch
License: MIT
Project-URL: Bug Tracker, https://github.com/aiidateam/aiida-sssp-workflow/issues
Classifier: License :: OSI Approved :: MIT License
Classifier: Operating System :: OS Independent
Classifier: Framework :: AiiDA
Classifier: Development Status :: 5 - Production/Stable
Classifier: Programming Language :: Python :: 3
Classifier: Programming Language :: Python :: 3 :: Only
Classifier: Programming Language :: Python :: 3.8
Classifier: Programming Language :: Python :: 3.9
Classifier: Programming Language :: Python :: 3.10
Requires-Python: >=3.8
License-File: LICENSE
Requires-Dist: aiida-core[atomic_tools] ~=2.4
Requires-Dist: aiida-quantumespresso ~=4.3.0
Provides-Extra: dev
Requires-Dist: bumpver ==2021.1114 ; extra == 'dev'
Requires-Dist: pre-commit ==2.10.0 ; extra == 'dev'
Provides-Extra: tests
Requires-Dist: pgtest >=1.3.1,~=1.3 ; extra == 'tests'
Requires-Dist: pytest ~=6.2 ; extra == 'tests'
Requires-Dist: pytest-regressions ~=2.2 ; extra == 'tests'
